qtwirl/__init__.py
qtwirl/_misc.py
qtwirl/_version.py
qtwirl/main.py
qtwirl/_builder/__init__.py
qtwirl/_builder/func.py
qtwirl/_parser/__init__.py
qtwirl/_parser/expander.py
qtwirl/_parser/inputs.py
qtwirl/_parser/readerconfig.py
qtwirl/_parser/selectionconfig.py
qtwirl/_parser/tableconfig.py
tests/expander/__init__.py
tests/expander/test_apply_default.py
tests/expander/test_config_expander.py
tests/expander/test_config_expander_config_keys.py
tests/expander/test_config_expander_default.py
tests/expander/test_expand_config.py
tests/expander/test_expand_config_shared.py
tests/expander/test_expand_one_dict.py
tests/expander/test_set_default.py
tests/main/__init__.py
tests/main/test_with_sample.py
tests/parser/__init__.py
tests/parser/test_expand_reader_config.py
tests/parser/test_expand_reader_config_flattern_reader.py
tests/parser/test_parse_data.py
tests/parser/selectionconfig/__init__.py
tests/parser/selectionconfig/test_complete_selection_cfg.py
tests/parser/selectionconfig/test_expand_selection_cfg.py
tests/parser/tableconfig/__init__.py
tests/parser/tableconfig/test_complete_table_cfg.py
tests/parser/tableconfig/test_complete_table_cfg_file_path.py
tests/parser/tableconfig/test_compose_tbl_filename.py
tests/parser/tableconfig/test_compose_tbl_filename_from_config.py
tests/parser/tableconfig/test_expand_table_cfg.py
qtwirl-0.9.2.dist-info/LICENSE
qtwirl-0.9.2.dist-info/METADATA
qtwirl-0.9.2.dist-info/WHEEL
qtwirl-0.9.2.dist-info/top_level.txt
qtwirl-0.9.2.dist-info/RECORD
