Metadata-Version: 2.1
Name: qtwirl
Version: 0.9.2
Summary: qtwirl (quick-twirl), a one-function interface to alphatwirl
Home-page: https://github.com/alphatwirl/qtwirl
Author: Tai Sakuma
Author-email: tai.sakuma@gmail.com
License: UNKNOWN
Platform: UNKNOWN
Classifier: Development Status :: 4 - Beta
Classifier: Intended Audience :: Science/Research
Classifier: License :: OSI Approved :: BSD License
Classifier: Programming Language :: Python :: 2.7
Classifier: Programming Language :: Python :: 3.6
Classifier: Programming Language :: Python :: 3.7
Requires-Dist: alphatwirl (>=0.23.2)
